gpp/__init__.py
gpp/algorithms.py
gpp/constants.py
gpp/datetimes.py
gpp/decorators.py
gpp/exceptions.py
gpp/geometry.py
gpp/loggers.py
gpp/networks.py
gpp/texts.py
gpp/contexts/__init__.py
gpp/contexts/menu.py
gpp/model/__init__.py
gpp/model/archive_mixins.py
gpp/model/base_mixins.py
gpp/model/exceptions.py
gpp/model/fields.py
gpp/model/geo_mixins.py
gpp/model/utils.py
gpp/static/css/app.css
gpp/static/css/bootstrap.css
gpp/static/css/waitMe.min.css
gpp/static/css/pages/auth.css
gpp/static/css/pages/chat.css
gpp/static/css/pages/dripicons.css
gpp/static/css/pages/email.css
gpp/static/css/pages/error.css
gpp/static/css/widgets/chat.css
gpp/static/css/widgets/todo.css
gpp/static/images/bg/4853433.jpg
gpp/static/images/faces/1.jpg
gpp/static/images/faces/2.jpg
gpp/static/images/faces/3.jpg
gpp/static/images/faces/4.jpg
gpp/static/images/faces/5.jpg
gpp/static/images/faces/6.jpg
gpp/static/images/faces/7.jpg
gpp/static/images/faces/8.jpg
gpp/static/images/logo/logo.png
gpp/static/images/samples/1.png
gpp/static/images/samples/2.png
gpp/static/images/samples/3.png
gpp/static/images/samples/4.png
gpp/static/images/samples/architecture1.jpg
gpp/static/images/samples/banana.jpg
gpp/static/images/samples/bg-mountain.jpg
gpp/static/images/samples/building.jpg
gpp/static/images/samples/error-403.png
gpp/static/images/samples/error-404.png
gpp/static/images/samples/error-500.png
gpp/static/images/samples/jump.jpg
gpp/static/images/samples/motorcycle.jpg
gpp/static/images/samples/origami.jpg
gpp/static/images/samples/water.jpg
gpp/static/js/bootstrap.bundle.min.js
gpp/static/js/bootstrap.min.js
gpp/static/js/bootstrap.min.js.map
gpp/static/js/fileupload.js
gpp/static/js/jquery-3.6.0.min.js
gpp/static/js/main.js
gpp/static/js/simpleXML.js
gpp/static/js/vendors.js
gpp/static/js/waitMe.min.js
gpp/static/js/extensions/rater-js.js
gpp/static/js/extensions/sweetalert2.js
gpp/static/js/extensions/toastify.js
gpp/static/js/pages/dashboard.js
gpp/static/js/pages/form-editor.js
py_extension_functions-0.0.9.dist-info/METADATA
py_extension_functions-0.0.9.dist-info/WHEEL
py_extension_functions-0.0.9.dist-info/RECORD
