Metadata-Version: 2.1
Name: py_extension_functions
Version: 0.0.9
Summary: personally, python extension functions
Project-URL: Download, https://pypi.org/project/py_extension_functions/
Project-URL: Homepage, https://github.com/Gaolious/py_extension_functions
Author: aJava
License: MIT
Classifier: Programming Language :: Python
Classifier: Programming Language :: Python :: 3.9
Classifier: Programming Language :: Python :: 3.10
Classifier: Programming Language :: Python :: 3.11
Requires-Python: >=3.9
Requires-Dist: django>=3.2
Requires-Dist: pytz>=2022.7.1
